aiva/core/__init__.py
aiva/core/assistants/__init__.py
aiva/core/assistants/classes/__init__.py
aiva/core/assistants/classes/aiva.py
aiva/core/chatbots/__init__.py
aiva/core/chatbots/classes/__init__.py
aiva/core/chatbots/classes/chat_gpt.py
aiva/core/exceptions/__init__.py
aiva/core/py.typed
aiva/core/types/__init__.py
aiva/core/utils/__init__.py
aiva/core/utils/classes/__init__.py
aiva/core/utils/classes/assistant.py
aiva/core/utils/classes/chat.py
aiva/core/utils/classes/chat_instances.py
aiva/core/utils/classes/chatbot.py
aiva/core/utils/classes/chatbot_classes.py
aiva/core/utils/classes/message.py
aiva/core/utils/classes/message_instances.py
aiva/core/utils/classes/payload.py
aiva/core/utils/classes/request.py
aiva/core/utils/classes/response.py
aiva/core/utils/classes/transaction.py
aiva/core/utils/classes/transaction_instances.py
aiva/core/utils/enums/__init__.py
aiva/core/utils/enums/role.py
aiva/core/utils/mixins/__init__.py
aiva/core/utils/mixins/instances.py
aiva_core-0.1.6.dist-info/METADATA
aiva_core-0.1.6.dist-info/LICENSE
aiva_core-0.1.6.dist-info/WHEEL
aiva_core-0.1.6.dist-info/RECORD
