Metadata-Version: 2.1
Name: aiva-core
Version: 0.1.6
Summary: A repository for AIVA, the AI Virtual Assistant written in Python.
License: MIT
Author: Sean O'Leary
Author-email: seamicole@gmail.com
Requires-Python: >=3.10,<4.0
Classifier: License :: OSI Approved :: MIT License
Classifier: Programming Language :: Python :: 3
Classifier: Programming Language :: Python :: 3.10
Classifier: Programming Language :: Python :: 3.11
Requires-Dist: openai (>=0.27.2,<0.28.0)
Requires-Dist: tiktoken (>=0.3.2,<0.4.0)
